frico_rtc/__init__.py
frico_rtc/blocks.py
frico_rtc/devices.py
frico_rtc/parsers.py
frico_rtc/py.typed
frico_rtc/states.py
frico_rtc-0.0.2.dist-info/LICENSE
frico_rtc-0.0.2.dist-info/METADATA
frico_rtc-0.0.2.dist-info/WHEEL
frico_rtc-0.0.2.dist-info/top_level.txt
frico_rtc-0.0.2.dist-info/RECORD
