Metadata-Version: 2.1
Name: frico-rtc
Version: 0.0.2
Summary: Python interface to Dallas/Maxim DS series RTCs (and others) using Frico
Home-page: https://github.com/mmangus/frico-rtc
Author: Michael Mangus
Author-email: mmangus@gmail.com
License: UNKNOWN
Project-URL: Bug Tracker, https://github.com/mmangus/frico-rtc/issues
Platform: UNKNOWN
Classifier: Programming Language :: Python :: 3
Classifier: License :: OSI Approved :: MIT License
Classifier: Operating System :: OS Independent
Requires-Python: >=3.6
Requires-Dist: frico (>=0.0.5)
